{
    "0":{
        "title": "A Cruz",
        "paragraph": "O braço esquerdo da Cruz de Cristo foi serrado em forma de Cruz e incrustada num relicário de Prata dourada, estilo gótico. E usualmente é apresentada aos fiéis após cada missa."
    },
    "1":{
        "title": "Caminhos a Santo Toribio",
        "paragraph": "A Ruta montañesa (72km) e a Ruta Asturiana (72km) partem do Caminho do Norte de Santiago, enquanto a Ruta Vadiniense (151km) e a Ruta Castellana (215km) se conectam com o Caminho Francês de Santiago."
    }
}